nbag/__init__.py
nbag/gen_wrappers.py
nbag/named_by_assignment.py
nbag-0.1.dist-info/LICENSE
nbag-0.1.dist-info/METADATA
nbag-0.1.dist-info/WHEEL
nbag-0.1.dist-info/top_level.txt
nbag-0.1.dist-info/RECORD
